bumpsemver/__init__.py
bumpsemver/__main__.py
bumpsemver/cli.py
bumpsemver/config.py
bumpsemver/discovery.py
bumpsemver/exceptions.py
bumpsemver/files/__init__.py
bumpsemver/files/base.py
bumpsemver/files/json.py
bumpsemver/files/text.py
bumpsemver/files/toml.py
bumpsemver/files/tomlpath.py
bumpsemver/files/yaml.py
bumpsemver/functions.py
bumpsemver/git.py
bumpsemver/utils.py
bumpsemver/version_part.py
bumpsemver-2.3.0.dist-info/LICENSE
bumpsemver-2.3.0.dist-info/METADATA
bumpsemver-2.3.0.dist-info/WHEEL
bumpsemver-2.3.0.dist-info/entry_points.txt
bumpsemver-2.3.0.dist-info/RECORD
