Metadata-Version: 2.1
Name: bumpsemver
Version: 2.3.0
Summary: Bump semver for git repos with a single command
Home-page: https://github.com/zhaow-de/bumpsemver
License: MIT
Keywords: bumpsemver,semver,version,release
Author: Zhao Wang
Author-email: zhaow.km@gmail.com
Requires-Python: >=3.10,<4
Classifier: Development Status :: 4 - Beta
Classifier: Environment :: Console
Classifier: Intended Audience :: Developers
Classifier: License :: OSI Approved :: MIT License
Classifier: Operating System :: OS Independent
Classifier: Programming Language :: Python
Classifier: Programming Language :: Python :: 3
Classifier: Programming Language :: Python :: 3.10
Classifier: Programming Language :: Python :: 3.11
Classifier: Programming Language :: Python :: 3.12
Classifier: Programming Language :: Python :: 3 :: Only
Classifier: Topic :: Software Development :: Build Tools
Classifier: Topic :: Software Development :: Version Control
Classifier: Topic :: System :: Software Distribution
Requires-Dist: jsonpath-ng
Requires-Dist: ruamel.yaml
Requires-Dist: tomlkit
Requires-Dist: yamlpath (>=3.4.1)
Project-URL: Repository, https://github.com/zhaow-de/bumpsemver
